{"cameraMode":{"drawMode":0,"name":"Shaded","section":"Shading Mode"},"sceneLighting":false,"audioPlay":false,"sceneViewState":{"m_AlwaysRefresh":false,"showFog":true,"showSkybox":false,"showFlares":true,"showImageEffects":true,"showParticleSystems":true,"showVisualEffectGraphs":true,"m_FxEnabled":true},"in2DMode":false,"pivot":{"x":0.3972458839416504,"y":0.2992541790008545,"z":-0.7317640781402588},"rotation":{"x":0.19029085338115693,"y":-0.615792453289032,"z":0.1565924733877182,"w":0.7483943700790405},"size":2.6322994232177736,"orthographic":false}